cloudreveimport
