Metadata-Version: 2.1
Name: cloudreveimport
Version: 1.2.1
Summary: Import your existing files into cloudreve!
Home-page: https://github.com/yindaheng98/cloudreveimport
Author: yindaheng98
Author-email: yindaheng98@gmail.com
License: UNKNOWN
Platform: UNKNOWN
Classifier: Programming Language :: Python :: 3
Classifier: License :: OSI Approved :: MIT License
Classifier: Operating System :: OS Independent
License-File: LICENSE
